{
    "estado": "Pendiente",
    "tipo": "B2C",
    "sucursalDeDistribucion": {
        "nomenclatura": "BAR",
        "descripcion": "BARRACAS",
        "id": "46"
    },
    "sucursalDeRendicion": {
        "nomenclatura": "REN",
        "descripcion": "PROVEEDOR RENDICIONES",
        "id": "-1"
    },
    "sucursalDeImposicion": {
        "nomenclatura": "",
        "descripcion": "",
        "id": ""
    },
    "fechaCreacion": "2020-05-06T15:47:57-03:00",
    "zonaDeReparto": "",
    "numeroDePermisionaria": "RNPSP Nº 586",
    "descripcionServicio": "Contrato de TEST WebService",
    "etiquetaRemito": "",
    "bultos": [
        {
            "numeroDeBulto": "1",
            "numeroDeEnvio": "360000000036820",
            "totalizador": "1/2",
            "linking": [
                {
                    "meta": "Etiqueta",
                    "contenido": "https://api.qa.andreani.com/v2/360000000036820/etiquetas"
                }
            ]
        },
        {
            "numeroDeBulto": "2",
            "numeroDeEnvio": "360000000036830",
            "totalizador": "2/2",
            "linking": [
                {
                    "meta": "Etiqueta",
                    "contenido": "https://api.qa.andreani.com/v2/360000000036830/etiquetas"
                }
            ]
        }
    ],
    "fechaEstimadaDeEntrega": "",
    "huellaDeCarbono": "",
    "gastoEnergetico": ""
}